{
  "isi": [
    {
      "id": "1",
      "fileNames": "FLY",
      "artists": "F/ACE",
      "driveFileNames": "F/ACE - FLY [Insert Song EP12 Tamon-kun Ima Docchi!?].mp3",
      "albums": "Tamon-kun Ima Docchi!? Insert Song EP12",
      "genres": "Anime",
      "years": "2026",
      "duration": "3:01",
      "driveLink": "https://drive.google.com/file/d/1xX9wEoMvnk43WESkUwhHLn3TxxpzsT2b/view?usp=drivesdk",
      "lyrics": "Lyrics Not Available (˚ ˃̣̣̥⌓˂̣̣̥ ), request on the ilkpop.wapzim.com forum for mp3 files with lyrics or add them yourself, search for lyrics from Google (❀❛ ֊ ❛„)♡",
      "coverUrl": "https://cdn.jsdelivr.net/gh/caraaink/meownime@0de94b3b83626649de8b46fa5f851829e27be59b/cover/anime/FACE_FLY.jpg",
      "bitrate_original": "320",
      "url_original": "https://drive.google.com/file/d/1xX9wEoMvnk43WESkUwhHLn3TxxpzsT2b/view?usp=drivesdk",
      "size_original": "7.4 MB",
      "bitrate_320": "320",
      "url_320": "https://drive.google.com/file/d/1xX9wEoMvnk43WESkUwhHLn3TxxpzsT2b/view?usp=drivesdk",
      "size_320": "7.4 MB",
      "driveFileNames_320": "F/ACE - FLY [Insert Song EP12 Tamon-kun Ima Docchi!?]-[320k].mp3",
      "bitrate_192": "192",
      "url_192": "https://drive.google.com/file/d/1FFXSHPOcX_Eny0_Nu64vEINDymVxKXlh/view?usp=drivesdk",
      "size_192": "4.4 MB",
      "driveFileNames_192": "F/ACE - FLY [Insert Song EP12 Tamon-kun Ima Docchi!?]-[192k].mp3",
      "bitrate_128": "128",
      "url_128": "https://drive.google.com/file/d/1pQhUfH7aVt7_JCzm_9vZf-sFp4IDYFFy/view?usp=drivesdk",
      "size_128": "3.0 MB",
      "driveFileNames_128": "F/ACE - FLY [Insert Song EP12 Tamon-kun Ima Docchi!?]-[128k].mp3",
      "lyrics_timestamp": "Fly high\nもっと高く (hey)\nもっと上に (hey)\n羽広げて\nWe are F/ACE\n\nつまんねぇって left 彷徨って right\nフラフラして day 無駄にした night\n努力なんてダセえって\n気付かない愚かな never ever\n自分のことばっか疑って周り見えなくなって\n何か残ったのか とっくに気づいてるんだろ?\n\n挫折はかつて\n夢だったもの 捨てずに集めて\n思い出になるまで\n\n向き合えば今\nMy dream my place\nもう離さない\nMy voice my song\n歌おう la ta ta\nMy wish my stage\n君に見せるよ\nMy wings my sound\n\nもっと高く fly high 今 fly high\n知らない世界 一緒に\n飛び立とう fly so high\n\nOh yeah 本当は頑張ってみたい\n一生懸命になりたい why\n今なら分かる失敗は悪くない\n君がくれた word\n変わるための power\nもう迷わない toward\n\nYeah, fly, are you ready? Ayy\n高くfly so high woo\n\nやっと気づいたよ君が\n僕を変えてくれたんだ\n\n手をかかげたら\nMy dream my place\n見えてくるほら\nMy voice my song\n歌おう la ta ta\nMy wish my stage\n君と作るよ\nMy wings my sound\n\nもっと早くfly high 行こう fly high\n知りたい (知りたい) 未来 (未来) 一緒に\n飛び立とうfly so high\n\n空へ\nFly high fly high\n完璧じゃなくてもいい\nFly high fly high\nちゃんと向き合えば\nFly high we can fly\n一緒に\nFly so high\n\nFly high\nもっと高く (hey)\nもっと上に (hey)\n羽広げて we are F/ACE\nFly high\n昇って高く (hey)\n前より高く (hey)\n飛べ空へと\nWe are F/ACE"
    }
  ]
}